{
  "books": [
    {
      "target": "phrase_出人意料",
      "file": "output/intro.en/gemma3/html/book_phrase_出人意料.html",
      "model": "gemma3"
    },
    {
      "target": "phrase_出人意料",
      "file": "output/intro.en/gemma4/html/book_phrase_出人意料.html",
      "model": "gemma4"
    }
  ],
  "generated_concepts": [
    {
      "name": "phrase_出人意料",
      "label": "Phrase 出人意料",
      "file": "output/intro.en/gemma3/html/concept_phrase_出人意料.html",
      "model": "gemma3"
    },
    {
      "name": "一",
      "label": "一",
      "file": "output/intro.en/gemma3/html/concept_一.html",
      "model": "gemma3"
    },
    {
      "name": "丷",
      "label": "丷",
      "file": "output/intro.en/gemma3/html/concept_丷.html",
      "model": "gemma3"
    },
    {
      "name": "亠",
      "label": "亠",
      "file": "output/intro.en/gemma3/html/concept_亠.html",
      "model": "gemma3"
    },
    {
      "name": "人",
      "label": "人",
      "file": "output/intro.en/gemma3/html/concept_人.html",
      "model": "gemma3"
    },
    {
      "name": "出",
      "label": "出",
      "file": "output/intro.en/gemma3/html/concept_出.html",
      "model": "gemma3"
    },
    {
      "name": "山",
      "label": "山",
      "file": "output/intro.en/gemma3/html/concept_山.html",
      "model": "gemma3"
    },
    {
      "name": "心",
      "label": "心",
      "file": "output/intro.en/gemma3/html/concept_心.html",
      "model": "gemma3"
    },
    {
      "name": "意",
      "label": "意",
      "file": "output/intro.en/gemma3/html/concept_意.html",
      "model": "gemma3"
    },
    {
      "name": "斗",
      "label": "斗",
      "file": "output/intro.en/gemma3/html/concept_斗.html",
      "model": "gemma3"
    },
    {
      "name": "料",
      "label": "料",
      "file": "output/intro.en/gemma3/html/concept_料.html",
      "model": "gemma3"
    },
    {
      "name": "日",
      "label": "日",
      "file": "output/intro.en/gemma3/html/concept_日.html",
      "model": "gemma3"
    },
    {
      "name": "木",
      "label": "木",
      "file": "output/intro.en/gemma3/html/concept_木.html",
      "model": "gemma3"
    },
    {
      "name": "立",
      "label": "立",
      "file": "output/intro.en/gemma3/html/concept_立.html",
      "model": "gemma3"
    },
    {
      "name": "米",
      "label": "米",
      "file": "output/intro.en/gemma3/html/concept_米.html",
      "model": "gemma3"
    },
    {
      "name": "音",
      "label": "音",
      "file": "output/intro.en/gemma3/html/concept_音.html",
      "model": "gemma3"
    },
    {
      "name": "phrase_出人意料",
      "label": "Phrase 出人意料",
      "file": "output/intro.en/gemma4/html/concept_phrase_出人意料.html",
      "model": "gemma4"
    },
    {
      "name": "一",
      "label": "一",
      "file": "output/intro.en/gemma4/html/concept_一.html",
      "model": "gemma4"
    },
    {
      "name": "丷",
      "label": "丷",
      "file": "output/intro.en/gemma4/html/concept_丷.html",
      "model": "gemma4"
    },
    {
      "name": "亠",
      "label": "亠",
      "file": "output/intro.en/gemma4/html/concept_亠.html",
      "model": "gemma4"
    },
    {
      "name": "人",
      "label": "人",
      "file": "output/intro.en/gemma4/html/concept_人.html",
      "model": "gemma4"
    },
    {
      "name": "出",
      "label": "出",
      "file": "output/intro.en/gemma4/html/concept_出.html",
      "model": "gemma4"
    },
    {
      "name": "山",
      "label": "山",
      "file": "output/intro.en/gemma4/html/concept_山.html",
      "model": "gemma4"
    },
    {
      "name": "心",
      "label": "心",
      "file": "output/intro.en/gemma4/html/concept_心.html",
      "model": "gemma4"
    },
    {
      "name": "意",
      "label": "意",
      "file": "output/intro.en/gemma4/html/concept_意.html",
      "model": "gemma4"
    },
    {
      "name": "斗",
      "label": "斗",
      "file": "output/intro.en/gemma4/html/concept_斗.html",
      "model": "gemma4"
    },
    {
      "name": "料",
      "label": "料",
      "file": "output/intro.en/gemma4/html/concept_料.html",
      "model": "gemma4"
    },
    {
      "name": "日",
      "label": "日",
      "file": "output/intro.en/gemma4/html/concept_日.html",
      "model": "gemma4"
    },
    {
      "name": "木",
      "label": "木",
      "file": "output/intro.en/gemma4/html/concept_木.html",
      "model": "gemma4"
    },
    {
      "name": "立",
      "label": "立",
      "file": "output/intro.en/gemma4/html/concept_立.html",
      "model": "gemma4"
    },
    {
      "name": "米",
      "label": "米",
      "file": "output/intro.en/gemma4/html/concept_米.html",
      "model": "gemma4"
    },
    {
      "name": "音",
      "label": "音",
      "file": "output/intro.en/gemma4/html/concept_音.html",
      "model": "gemma4"
    }
  ]
}
