{
  "books": [
    {
      "target": "phrase_千方百计",
      "file": "output/intro.ar/default/html/book_phrase_千方百计.html",
      "model": "default"
    },
    {
      "target": "phrase_千方百计",
      "file": "output/intro.ar/sonnet/html/book_phrase_千方百计.html",
      "model": "sonnet"
    },
    {
      "target": "phrase_千方百计",
      "file": "output/intro.de/default/html/book_phrase_千方百计.html",
      "model": "default"
    },
    {
      "target": "phrase_千方百计",
      "file": "output/intro.de/gemma4/html/book_phrase_千方百计.html",
      "model": "gemma4"
    },
    {
      "target": "phrase_千方百计",
      "file": "output/intro.de/sonnet/html/book_phrase_千方百计.html",
      "model": "sonnet"
    },
    {
      "target": "phrase_千方百计",
      "file": "output/intro.en/default/html/book_phrase_千方百计.html",
      "model": "default"
    },
    {
      "target": "phrase_千方百计",
      "file": "output/intro.en/gemma3/html/book_phrase_千方百计.html",
      "model": "gemma3"
    },
    {
      "target": "phrase_千方百计",
      "file": "output/intro.en/gemma4/html/book_phrase_千方百计.html",
      "model": "gemma4"
    },
    {
      "target": "phrase_千方百计",
      "file": "output/intro.en/sonnet/html/book_phrase_千方百计.html",
      "model": "sonnet"
    },
    {
      "target": "phrase_千方百计",
      "file": "output/intro.es/default/html/book_phrase_千方百计.html",
      "model": "default"
    },
    {
      "target": "phrase_千方百计",
      "file": "output/intro.es/gemma4/html/book_phrase_千方百计.html",
      "model": "gemma4"
    },
    {
      "target": "phrase_千方百计",
      "file": "output/intro.es/sonnet/html/book_phrase_千方百计.html",
      "model": "sonnet"
    },
    {
      "target": "phrase_千方百计",
      "file": "output/intro.fr/default/html/book_phrase_千方百计.html",
      "model": "default"
    },
    {
      "target": "phrase_千方百计",
      "file": "output/intro.fr/gemma4/html/book_phrase_千方百计.html",
      "model": "gemma4"
    },
    {
      "target": "phrase_千方百计",
      "file": "output/intro.fr/sonnet/html/book_phrase_千方百计.html",
      "model": "sonnet"
    },
    {
      "target": "phrase_千方百计",
      "file": "output/intro.ko/sonnet/html/phrase_千方百计.html",
      "model": "sonnet"
    },
    {
      "target": "phrase_千方百计",
      "file": "output/intro.zh/default/html/book_phrase_千方百计.html",
      "model": "default"
    },
    {
      "target": "phrase_千方百计",
      "file": "output/intro.zh/gemma3/html/book_phrase_千方百计.html",
      "model": "gemma3"
    },
    {
      "target": "phrase_千方百计",
      "file": "output/intro.zh/gemma4/html/book_phrase_千方百计.html",
      "model": "gemma4"
    },
    {
      "target": "phrase_千方百计",
      "file": "output/intro.zh/sonnet/html/book_phrase_千方百计.html",
      "model": "sonnet"
    }
  ],
  "generated_concepts": [
    {
      "name": "phrase_千方百计",
      "label": "Phrase 千方百计",
      "file": "output/intro.ar/default/html/concept_phrase_千方百计.html",
      "model": "default",
      "pinyin": "qianfangbaiji",
      "pinyin_initials": "qfbj"
    },
    {
      "name": "一",
      "label": "一",
      "file": "output/intro.ar/default/html/concept_一.html",
      "model": "default",
      "pinyin": "yi"
    },
    {
      "name": "万",
      "label": "万",
      "file": "output/intro.ar/default/html/concept_万.html",
      "model": "default",
      "pinyin": "wan"
    },
    {
      "name": "丨",
      "label": "丨",
      "file": "output/intro.ar/default/html/concept_丨.html",
      "model": "default",
      "pinyin": "shu"
    },
    {
      "name": "丶",
      "label": "丶",
      "file": "output/intro.ar/default/html/concept_丶.html",
      "model": "default",
      "pinyin": "zhu"
    },
    {
      "name": "丿",
      "label": "丿",
      "file": "output/intro.ar/default/html/concept_丿.html",
      "model": "default",
      "pinyin": "pie"
    },
    {
      "name": "十",
      "label": "十",
      "file": "output/intro.ar/default/html/concept_十.html",
      "model": "default",
      "pinyin": "shi"
    },
    {
      "name": "千",
      "label": "千",
      "file": "output/intro.ar/default/html/concept_千.html",
      "model": "default",
      "pinyin": "qian"
    },
    {
      "name": "方",
      "label": "方",
      "file": "output/intro.ar/default/html/concept_方.html",
      "model": "default",
      "pinyin": "fang"
    },
    {
      "name": "日",
      "label": "日",
      "file": "output/intro.ar/default/html/concept_日.html",
      "model": "default",
      "pinyin": "ri"
    },
    {
      "name": "白",
      "label": "白",
      "file": "output/intro.ar/default/html/concept_白.html",
      "model": "default",
      "pinyin": "bai"
    },
    {
      "name": "百",
      "label": "百",
      "file": "output/intro.ar/default/html/concept_百.html",
      "model": "default",
      "pinyin": "bai"
    },
    {
      "name": "讠",
      "label": "讠",
      "file": "output/intro.ar/default/html/concept_讠.html",
      "model": "default",
      "pinyin": "yan"
    },
    {
      "name": "计",
      "label": "计",
      "file": "output/intro.ar/default/html/concept_计.html",
      "model": "default",
      "pinyin": "ji"
    },
    {
      "name": "phrase_千方百计",
      "label": "Phrase 千方百计",
      "file": "output/intro.ar/sonnet/html/concept_phrase_千方百计.html",
      "model": "sonnet",
      "pinyin": "qianfangbaiji",
      "pinyin_initials": "qfbj"
    },
    {
      "name": "一",
      "label": "一",
      "file": "output/intro.ar/sonnet/html/concept_一.html",
      "model": "sonnet",
      "pinyin": "yi"
    },
    {
      "name": "万",
      "label": "万",
      "file": "output/intro.ar/sonnet/html/concept_万.html",
      "model": "sonnet",
      "pinyin": "wan"
    },
    {
      "name": "丨",
      "label": "丨",
      "file": "output/intro.ar/sonnet/html/concept_丨.html",
      "model": "sonnet",
      "pinyin": "shu"
    },
    {
      "name": "丶",
      "label": "丶",
      "file": "output/intro.ar/sonnet/html/concept_丶.html",
      "model": "sonnet",
      "pinyin": "zhu"
    },
    {
      "name": "丿",
      "label": "丿",
      "file": "output/intro.ar/sonnet/html/concept_丿.html",
      "model": "sonnet",
      "pinyin": "pie"
    },
    {
      "name": "十",
      "label": "十",
      "file": "output/intro.ar/sonnet/html/concept_十.html",
      "model": "sonnet",
      "pinyin": "shi"
    },
    {
      "name": "千",
      "label": "千",
      "file": "output/intro.ar/sonnet/html/concept_千.html",
      "model": "sonnet",
      "pinyin": "qian"
    },
    {
      "name": "方",
      "label": "方",
      "file": "output/intro.ar/sonnet/html/concept_方.html",
      "model": "sonnet",
      "pinyin": "fang"
    },
    {
      "name": "日",
      "label": "日",
      "file": "output/intro.ar/sonnet/html/concept_日.html",
      "model": "sonnet",
      "pinyin": "ri"
    },
    {
      "name": "白",
      "label": "白",
      "file": "output/intro.ar/sonnet/html/concept_白.html",
      "model": "sonnet",
      "pinyin": "bai"
    },
    {
      "name": "百",
      "label": "百",
      "file": "output/intro.ar/sonnet/html/concept_百.html",
      "model": "sonnet",
      "pinyin": "bai"
    },
    {
      "name": "讠",
      "label": "讠",
      "file": "output/intro.ar/sonnet/html/concept_讠.html",
      "model": "sonnet",
      "pinyin": "yan"
    },
    {
      "name": "计",
      "label": "计",
      "file": "output/intro.ar/sonnet/html/concept_计.html",
      "model": "sonnet",
      "pinyin": "ji"
    },
    {
      "name": "phrase_千方百计",
      "label": "Phrase 千方百计",
      "file": "output/intro.de/default/html/concept_phrase_千方百计.html",
      "model": "default",
      "pinyin": "qianfangbaiji",
      "pinyin_initials": "qfbj"
    },
    {
      "name": "一",
      "label": "一",
      "file": "output/intro.de/default/html/concept_一.html",
      "model": "default",
      "pinyin": "yi"
    },
    {
      "name": "万",
      "label": "万",
      "file": "output/intro.de/default/html/concept_万.html",
      "model": "default",
      "pinyin": "wan"
    },
    {
      "name": "丨",
      "label": "丨",
      "file": "output/intro.de/default/html/concept_丨.html",
      "model": "default",
      "pinyin": "shu"
    },
    {
      "name": "丶",
      "label": "丶",
      "file": "output/intro.de/default/html/concept_丶.html",
      "model": "default",
      "pinyin": "zhu"
    },
    {
      "name": "丿",
      "label": "丿",
      "file": "output/intro.de/default/html/concept_丿.html",
      "model": "default",
      "pinyin": "pie"
    },
    {
      "name": "十",
      "label": "十",
      "file": "output/intro.de/default/html/concept_十.html",
      "model": "default",
      "pinyin": "shi"
    },
    {
      "name": "千",
      "label": "千",
      "file": "output/intro.de/default/html/concept_千.html",
      "model": "default",
      "pinyin": "qian"
    },
    {
      "name": "方",
      "label": "方",
      "file": "output/intro.de/default/html/concept_方.html",
      "model": "default",
      "pinyin": "fang"
    },
    {
      "name": "日",
      "label": "日",
      "file": "output/intro.de/default/html/concept_日.html",
      "model": "default",
      "pinyin": "ri"
    },
    {
      "name": "白",
      "label": "白",
      "file": "output/intro.de/default/html/concept_白.html",
      "model": "default",
      "pinyin": "bai"
    },
    {
      "name": "百",
      "label": "百",
      "file": "output/intro.de/default/html/concept_百.html",
      "model": "default",
      "pinyin": "bai"
    },
    {
      "name": "讠",
      "label": "讠",
      "file": "output/intro.de/default/html/concept_讠.html",
      "model": "default",
      "pinyin": "yan"
    },
    {
      "name": "计",
      "label": "计",
      "file": "output/intro.de/default/html/concept_计.html",
      "model": "default",
      "pinyin": "ji"
    },
    {
      "name": "phrase_千方百计",
      "label": "Phrase 千方百计",
      "file": "output/intro.de/gemma4/html/concept_phrase_千方百计.html",
      "model": "gemma4",
      "pinyin": "qianfangbaiji",
      "pinyin_initials": "qfbj"
    },
    {
      "name": "一",
      "label": "一",
      "file": "output/intro.de/gemma4/html/concept_一.html",
      "model": "gemma4",
      "pinyin": "yi"
    },
    {
      "name": "万",
      "label": "万",
      "file": "output/intro.de/gemma4/html/concept_万.html",
      "model": "gemma4",
      "pinyin": "wan"
    },
    {
      "name": "丨",
      "label": "丨",
      "file": "output/intro.de/gemma4/html/concept_丨.html",
      "model": "gemma4",
      "pinyin": "shu"
    },
    {
      "name": "丶",
      "label": "丶",
      "file": "output/intro.de/gemma4/html/concept_丶.html",
      "model": "gemma4",
      "pinyin": "zhu"
    },
    {
      "name": "丿",
      "label": "丿",
      "file": "output/intro.de/gemma4/html/concept_丿.html",
      "model": "gemma4",
      "pinyin": "pie"
    },
    {
      "name": "十",
      "label": "十",
      "file": "output/intro.de/gemma4/html/concept_十.html",
      "model": "gemma4",
      "pinyin": "shi"
    },
    {
      "name": "千",
      "label": "千",
      "file": "output/intro.de/gemma4/html/concept_千.html",
      "model": "gemma4",
      "pinyin": "qian"
    },
    {
      "name": "方",
      "label": "方",
      "file": "output/intro.de/gemma4/html/concept_方.html",
      "model": "gemma4",
      "pinyin": "fang"
    },
    {
      "name": "日",
      "label": "日",
      "file": "output/intro.de/gemma4/html/concept_日.html",
      "model": "gemma4",
      "pinyin": "ri"
    },
    {
      "name": "白",
      "label": "白",
      "file": "output/intro.de/gemma4/html/concept_白.html",
      "model": "gemma4",
      "pinyin": "bai"
    },
    {
      "name": "百",
      "label": "百",
      "file": "output/intro.de/gemma4/html/concept_百.html",
      "model": "gemma4",
      "pinyin": "bai"
    },
    {
      "name": "讠",
      "label": "讠",
      "file": "output/intro.de/gemma4/html/concept_讠.html",
      "model": "gemma4",
      "pinyin": "yan"
    },
    {
      "name": "计",
      "label": "计",
      "file": "output/intro.de/gemma4/html/concept_计.html",
      "model": "gemma4",
      "pinyin": "ji"
    },
    {
      "name": "phrase_千方百计",
      "label": "Phrase 千方百计",
      "file": "output/intro.de/sonnet/html/concept_phrase_千方百计.html",
      "model": "sonnet",
      "pinyin": "qianfangbaiji",
      "pinyin_initials": "qfbj"
    },
    {
      "name": "一",
      "label": "一",
      "file": "output/intro.de/sonnet/html/concept_一.html",
      "model": "sonnet",
      "pinyin": "yi"
    },
    {
      "name": "万",
      "label": "万",
      "file": "output/intro.de/sonnet/html/concept_万.html",
      "model": "sonnet",
      "pinyin": "wan"
    },
    {
      "name": "丨",
      "label": "丨",
      "file": "output/intro.de/sonnet/html/concept_丨.html",
      "model": "sonnet",
      "pinyin": "shu"
    },
    {
      "name": "丶",
      "label": "丶",
      "file": "output/intro.de/sonnet/html/concept_丶.html",
      "model": "sonnet",
      "pinyin": "zhu"
    },
    {
      "name": "丿",
      "label": "丿",
      "file": "output/intro.de/sonnet/html/concept_丿.html",
      "model": "sonnet",
      "pinyin": "pie"
    },
    {
      "name": "十",
      "label": "十",
      "file": "output/intro.de/sonnet/html/concept_十.html",
      "model": "sonnet",
      "pinyin": "shi"
    },
    {
      "name": "千",
      "label": "千",
      "file": "output/intro.de/sonnet/html/concept_千.html",
      "model": "sonnet",
      "pinyin": "qian"
    },
    {
      "name": "方",
      "label": "方",
      "file": "output/intro.de/sonnet/html/concept_方.html",
      "model": "sonnet",
      "pinyin": "fang"
    },
    {
      "name": "日",
      "label": "日",
      "file": "output/intro.de/sonnet/html/concept_日.html",
      "model": "sonnet",
      "pinyin": "ri"
    },
    {
      "name": "白",
      "label": "白",
      "file": "output/intro.de/sonnet/html/concept_白.html",
      "model": "sonnet",
      "pinyin": "bai"
    },
    {
      "name": "百",
      "label": "百",
      "file": "output/intro.de/sonnet/html/concept_百.html",
      "model": "sonnet",
      "pinyin": "bai"
    },
    {
      "name": "讠",
      "label": "讠",
      "file": "output/intro.de/sonnet/html/concept_讠.html",
      "model": "sonnet",
      "pinyin": "yan"
    },
    {
      "name": "计",
      "label": "计",
      "file": "output/intro.de/sonnet/html/concept_计.html",
      "model": "sonnet",
      "pinyin": "ji"
    },
    {
      "name": "phrase_千方百计",
      "label": "Phrase 千方百计",
      "file": "output/intro.en/default/html/concept_phrase_千方百计.html",
      "model": "default",
      "pinyin": "qianfangbaiji",
      "pinyin_initials": "qfbj"
    },
    {
      "name": "一",
      "label": "一",
      "file": "output/intro.en/default/html/concept_一.html",
      "model": "default",
      "pinyin": "yi"
    },
    {
      "name": "万",
      "label": "万",
      "file": "output/intro.en/default/html/concept_万.html",
      "model": "default",
      "pinyin": "wan"
    },
    {
      "name": "丨",
      "label": "丨",
      "file": "output/intro.en/default/html/concept_丨.html",
      "model": "default",
      "pinyin": "shu"
    },
    {
      "name": "丶",
      "label": "丶",
      "file": "output/intro.en/default/html/concept_丶.html",
      "model": "default",
      "pinyin": "zhu"
    },
    {
      "name": "丿",
      "label": "丿",
      "file": "output/intro.en/default/html/concept_丿.html",
      "model": "default",
      "pinyin": "pie"
    },
    {
      "name": "十",
      "label": "十",
      "file": "output/intro.en/default/html/concept_十.html",
      "model": "default",
      "pinyin": "shi"
    },
    {
      "name": "千",
      "label": "千",
      "file": "output/intro.en/default/html/concept_千.html",
      "model": "default",
      "pinyin": "qian"
    },
    {
      "name": "方",
      "label": "方",
      "file": "output/intro.en/default/html/concept_方.html",
      "model": "default",
      "pinyin": "fang"
    },
    {
      "name": "日",
      "label": "日",
      "file": "output/intro.en/default/html/concept_日.html",
      "model": "default",
      "pinyin": "ri"
    },
    {
      "name": "白",
      "label": "白",
      "file": "output/intro.en/default/html/concept_白.html",
      "model": "default",
      "pinyin": "bai"
    },
    {
      "name": "百",
      "label": "百",
      "file": "output/intro.en/default/html/concept_百.html",
      "model": "default",
      "pinyin": "bai"
    },
    {
      "name": "讠",
      "label": "讠",
      "file": "output/intro.en/default/html/concept_讠.html",
      "model": "default",
      "pinyin": "yan"
    },
    {
      "name": "计",
      "label": "计",
      "file": "output/intro.en/default/html/concept_计.html",
      "model": "default",
      "pinyin": "ji"
    },
    {
      "name": "phrase_千方百计",
      "label": "Phrase 千方百计",
      "file": "output/intro.en/gemma3/html/concept_phrase_千方百计.html",
      "model": "gemma3",
      "pinyin": "qianfangbaiji",
      "pinyin_initials": "qfbj"
    },
    {
      "name": "一",
      "label": "一",
      "file": "output/intro.en/gemma3/html/concept_一.html",
      "model": "gemma3",
      "pinyin": "yi"
    },
    {
      "name": "万",
      "label": "万",
      "file": "output/intro.en/gemma3/html/concept_万.html",
      "model": "gemma3",
      "pinyin": "wan"
    },
    {
      "name": "丨",
      "label": "丨",
      "file": "output/intro.en/gemma3/html/concept_丨.html",
      "model": "gemma3",
      "pinyin": "shu"
    },
    {
      "name": "丶",
      "label": "丶",
      "file": "output/intro.en/gemma3/html/concept_丶.html",
      "model": "gemma3",
      "pinyin": "zhu"
    },
    {
      "name": "丿",
      "label": "丿",
      "file": "output/intro.en/gemma3/html/concept_丿.html",
      "model": "gemma3",
      "pinyin": "pie"
    },
    {
      "name": "十",
      "label": "十",
      "file": "output/intro.en/gemma3/html/concept_十.html",
      "model": "gemma3",
      "pinyin": "shi"
    },
    {
      "name": "千",
      "label": "千",
      "file": "output/intro.en/gemma3/html/concept_千.html",
      "model": "gemma3",
      "pinyin": "qian"
    },
    {
      "name": "方",
      "label": "方",
      "file": "output/intro.en/gemma3/html/concept_方.html",
      "model": "gemma3",
      "pinyin": "fang"
    },
    {
      "name": "日",
      "label": "日",
      "file": "output/intro.en/gemma3/html/concept_日.html",
      "model": "gemma3",
      "pinyin": "ri"
    },
    {
      "name": "白",
      "label": "白",
      "file": "output/intro.en/gemma3/html/concept_白.html",
      "model": "gemma3",
      "pinyin": "bai"
    },
    {
      "name": "百",
      "label": "百",
      "file": "output/intro.en/gemma3/html/concept_百.html",
      "model": "gemma3",
      "pinyin": "bai"
    },
    {
      "name": "讠",
      "label": "讠",
      "file": "output/intro.en/gemma3/html/concept_讠.html",
      "model": "gemma3",
      "pinyin": "yan"
    },
    {
      "name": "计",
      "label": "计",
      "file": "output/intro.en/gemma3/html/concept_计.html",
      "model": "gemma3",
      "pinyin": "ji"
    },
    {
      "name": "phrase_千方百计",
      "label": "Phrase 千方百计",
      "file": "output/intro.en/gemma4/html/concept_phrase_千方百计.html",
      "model": "gemma4",
      "pinyin": "qianfangbaiji",
      "pinyin_initials": "qfbj"
    },
    {
      "name": "一",
      "label": "一",
      "file": "output/intro.en/gemma4/html/concept_一.html",
      "model": "gemma4",
      "pinyin": "yi"
    },
    {
      "name": "万",
      "label": "万",
      "file": "output/intro.en/gemma4/html/concept_万.html",
      "model": "gemma4",
      "pinyin": "wan"
    },
    {
      "name": "丨",
      "label": "丨",
      "file": "output/intro.en/gemma4/html/concept_丨.html",
      "model": "gemma4",
      "pinyin": "shu"
    },
    {
      "name": "丶",
      "label": "丶",
      "file": "output/intro.en/gemma4/html/concept_丶.html",
      "model": "gemma4",
      "pinyin": "zhu"
    },
    {
      "name": "丿",
      "label": "丿",
      "file": "output/intro.en/gemma4/html/concept_丿.html",
      "model": "gemma4",
      "pinyin": "pie"
    },
    {
      "name": "十",
      "label": "十",
      "file": "output/intro.en/gemma4/html/concept_十.html",
      "model": "gemma4",
      "pinyin": "shi"
    },
    {
      "name": "千",
      "label": "千",
      "file": "output/intro.en/gemma4/html/concept_千.html",
      "model": "gemma4",
      "pinyin": "qian"
    },
    {
      "name": "方",
      "label": "方",
      "file": "output/intro.en/gemma4/html/concept_方.html",
      "model": "gemma4",
      "pinyin": "fang"
    },
    {
      "name": "日",
      "label": "日",
      "file": "output/intro.en/gemma4/html/concept_日.html",
      "model": "gemma4",
      "pinyin": "ri"
    },
    {
      "name": "白",
      "label": "白",
      "file": "output/intro.en/gemma4/html/concept_白.html",
      "model": "gemma4",
      "pinyin": "bai"
    },
    {
      "name": "百",
      "label": "百",
      "file": "output/intro.en/gemma4/html/concept_百.html",
      "model": "gemma4",
      "pinyin": "bai"
    },
    {
      "name": "讠",
      "label": "讠",
      "file": "output/intro.en/gemma4/html/concept_讠.html",
      "model": "gemma4",
      "pinyin": "yan"
    },
    {
      "name": "计",
      "label": "计",
      "file": "output/intro.en/gemma4/html/concept_计.html",
      "model": "gemma4",
      "pinyin": "ji"
    },
    {
      "name": "phrase_千方百计",
      "label": "Phrase 千方百计",
      "file": "output/intro.en/sonnet/html/concept_phrase_千方百计.html",
      "model": "sonnet",
      "pinyin": "qianfangbaiji",
      "pinyin_initials": "qfbj"
    },
    {
      "name": "一",
      "label": "一",
      "file": "output/intro.en/sonnet/html/concept_一.html",
      "model": "sonnet",
      "pinyin": "yi"
    },
    {
      "name": "万",
      "label": "万",
      "file": "output/intro.en/sonnet/html/concept_万.html",
      "model": "sonnet",
      "pinyin": "wan"
    },
    {
      "name": "丨",
      "label": "丨",
      "file": "output/intro.en/sonnet/html/concept_丨.html",
      "model": "sonnet",
      "pinyin": "shu"
    },
    {
      "name": "丶",
      "label": "丶",
      "file": "output/intro.en/sonnet/html/concept_丶.html",
      "model": "sonnet",
      "pinyin": "zhu"
    },
    {
      "name": "丿",
      "label": "丿",
      "file": "output/intro.en/sonnet/html/concept_丿.html",
      "model": "sonnet",
      "pinyin": "pie"
    },
    {
      "name": "十",
      "label": "十",
      "file": "output/intro.en/sonnet/html/concept_十.html",
      "model": "sonnet",
      "pinyin": "shi"
    },
    {
      "name": "千",
      "label": "千",
      "file": "output/intro.en/sonnet/html/concept_千.html",
      "model": "sonnet",
      "pinyin": "qian"
    },
    {
      "name": "方",
      "label": "方",
      "file": "output/intro.en/sonnet/html/concept_方.html",
      "model": "sonnet",
      "pinyin": "fang"
    },
    {
      "name": "日",
      "label": "日",
      "file": "output/intro.en/sonnet/html/concept_日.html",
      "model": "sonnet",
      "pinyin": "ri"
    },
    {
      "name": "白",
      "label": "白",
      "file": "output/intro.en/sonnet/html/concept_白.html",
      "model": "sonnet",
      "pinyin": "bai"
    },
    {
      "name": "百",
      "label": "百",
      "file": "output/intro.en/sonnet/html/concept_百.html",
      "model": "sonnet",
      "pinyin": "bai"
    },
    {
      "name": "讠",
      "label": "讠",
      "file": "output/intro.en/sonnet/html/concept_讠.html",
      "model": "sonnet",
      "pinyin": "yan"
    },
    {
      "name": "计",
      "label": "计",
      "file": "output/intro.en/sonnet/html/concept_计.html",
      "model": "sonnet",
      "pinyin": "ji"
    },
    {
      "name": "phrase_千方百计",
      "label": "Phrase 千方百计",
      "file": "output/intro.es/default/html/concept_phrase_千方百计.html",
      "model": "default",
      "pinyin": "qianfangbaiji",
      "pinyin_initials": "qfbj"
    },
    {
      "name": "一",
      "label": "一",
      "file": "output/intro.es/default/html/concept_一.html",
      "model": "default",
      "pinyin": "yi"
    },
    {
      "name": "万",
      "label": "万",
      "file": "output/intro.es/default/html/concept_万.html",
      "model": "default",
      "pinyin": "wan"
    },
    {
      "name": "丨",
      "label": "丨",
      "file": "output/intro.es/default/html/concept_丨.html",
      "model": "default",
      "pinyin": "shu"
    },
    {
      "name": "丶",
      "label": "丶",
      "file": "output/intro.es/default/html/concept_丶.html",
      "model": "default",
      "pinyin": "zhu"
    },
    {
      "name": "丿",
      "label": "丿",
      "file": "output/intro.es/default/html/concept_丿.html",
      "model": "default",
      "pinyin": "pie"
    },
    {
      "name": "十",
      "label": "十",
      "file": "output/intro.es/default/html/concept_十.html",
      "model": "default",
      "pinyin": "shi"
    },
    {
      "name": "千",
      "label": "千",
      "file": "output/intro.es/default/html/concept_千.html",
      "model": "default",
      "pinyin": "qian"
    },
    {
      "name": "方",
      "label": "方",
      "file": "output/intro.es/default/html/concept_方.html",
      "model": "default",
      "pinyin": "fang"
    },
    {
      "name": "日",
      "label": "日",
      "file": "output/intro.es/default/html/concept_日.html",
      "model": "default",
      "pinyin": "ri"
    },
    {
      "name": "白",
      "label": "白",
      "file": "output/intro.es/default/html/concept_白.html",
      "model": "default",
      "pinyin": "bai"
    },
    {
      "name": "百",
      "label": "百",
      "file": "output/intro.es/default/html/concept_百.html",
      "model": "default",
      "pinyin": "bai"
    },
    {
      "name": "讠",
      "label": "讠",
      "file": "output/intro.es/default/html/concept_讠.html",
      "model": "default",
      "pinyin": "yan"
    },
    {
      "name": "计",
      "label": "计",
      "file": "output/intro.es/default/html/concept_计.html",
      "model": "default",
      "pinyin": "ji"
    },
    {
      "name": "phrase_千方百计",
      "label": "Phrase 千方百计",
      "file": "output/intro.es/gemma4/html/concept_phrase_千方百计.html",
      "model": "gemma4",
      "pinyin": "qianfangbaiji",
      "pinyin_initials": "qfbj"
    },
    {
      "name": "一",
      "label": "一",
      "file": "output/intro.es/gemma4/html/concept_一.html",
      "model": "gemma4",
      "pinyin": "yi"
    },
    {
      "name": "万",
      "label": "万",
      "file": "output/intro.es/gemma4/html/concept_万.html",
      "model": "gemma4",
      "pinyin": "wan"
    },
    {
      "name": "丨",
      "label": "丨",
      "file": "output/intro.es/gemma4/html/concept_丨.html",
      "model": "gemma4",
      "pinyin": "shu"
    },
    {
      "name": "丶",
      "label": "丶",
      "file": "output/intro.es/gemma4/html/concept_丶.html",
      "model": "gemma4",
      "pinyin": "zhu"
    },
    {
      "name": "丿",
      "label": "丿",
      "file": "output/intro.es/gemma4/html/concept_丿.html",
      "model": "gemma4",
      "pinyin": "pie"
    },
    {
      "name": "十",
      "label": "十",
      "file": "output/intro.es/gemma4/html/concept_十.html",
      "model": "gemma4",
      "pinyin": "shi"
    },
    {
      "name": "千",
      "label": "千",
      "file": "output/intro.es/gemma4/html/concept_千.html",
      "model": "gemma4",
      "pinyin": "qian"
    },
    {
      "name": "方",
      "label": "方",
      "file": "output/intro.es/gemma4/html/concept_方.html",
      "model": "gemma4",
      "pinyin": "fang"
    },
    {
      "name": "日",
      "label": "日",
      "file": "output/intro.es/gemma4/html/concept_日.html",
      "model": "gemma4",
      "pinyin": "ri"
    },
    {
      "name": "白",
      "label": "白",
      "file": "output/intro.es/gemma4/html/concept_白.html",
      "model": "gemma4",
      "pinyin": "bai"
    },
    {
      "name": "百",
      "label": "百",
      "file": "output/intro.es/gemma4/html/concept_百.html",
      "model": "gemma4",
      "pinyin": "bai"
    },
    {
      "name": "讠",
      "label": "讠",
      "file": "output/intro.es/gemma4/html/concept_讠.html",
      "model": "gemma4",
      "pinyin": "yan"
    },
    {
      "name": "计",
      "label": "计",
      "file": "output/intro.es/gemma4/html/concept_计.html",
      "model": "gemma4",
      "pinyin": "ji"
    },
    {
      "name": "phrase_千方百计",
      "label": "Phrase 千方百计",
      "file": "output/intro.es/sonnet/html/concept_phrase_千方百计.html",
      "model": "sonnet",
      "pinyin": "qianfangbaiji",
      "pinyin_initials": "qfbj"
    },
    {
      "name": "一",
      "label": "一",
      "file": "output/intro.es/sonnet/html/concept_一.html",
      "model": "sonnet",
      "pinyin": "yi"
    },
    {
      "name": "万",
      "label": "万",
      "file": "output/intro.es/sonnet/html/concept_万.html",
      "model": "sonnet",
      "pinyin": "wan"
    },
    {
      "name": "丨",
      "label": "丨",
      "file": "output/intro.es/sonnet/html/concept_丨.html",
      "model": "sonnet",
      "pinyin": "shu"
    },
    {
      "name": "丶",
      "label": "丶",
      "file": "output/intro.es/sonnet/html/concept_丶.html",
      "model": "sonnet",
      "pinyin": "zhu"
    },
    {
      "name": "丿",
      "label": "丿",
      "file": "output/intro.es/sonnet/html/concept_丿.html",
      "model": "sonnet",
      "pinyin": "pie"
    },
    {
      "name": "十",
      "label": "十",
      "file": "output/intro.es/sonnet/html/concept_十.html",
      "model": "sonnet",
      "pinyin": "shi"
    },
    {
      "name": "千",
      "label": "千",
      "file": "output/intro.es/sonnet/html/concept_千.html",
      "model": "sonnet",
      "pinyin": "qian"
    },
    {
      "name": "方",
      "label": "方",
      "file": "output/intro.es/sonnet/html/concept_方.html",
      "model": "sonnet",
      "pinyin": "fang"
    },
    {
      "name": "日",
      "label": "日",
      "file": "output/intro.es/sonnet/html/concept_日.html",
      "model": "sonnet",
      "pinyin": "ri"
    },
    {
      "name": "白",
      "label": "白",
      "file": "output/intro.es/sonnet/html/concept_白.html",
      "model": "sonnet",
      "pinyin": "bai"
    },
    {
      "name": "百",
      "label": "百",
      "file": "output/intro.es/sonnet/html/concept_百.html",
      "model": "sonnet",
      "pinyin": "bai"
    },
    {
      "name": "讠",
      "label": "讠",
      "file": "output/intro.es/sonnet/html/concept_讠.html",
      "model": "sonnet",
      "pinyin": "yan"
    },
    {
      "name": "计",
      "label": "计",
      "file": "output/intro.es/sonnet/html/concept_计.html",
      "model": "sonnet",
      "pinyin": "ji"
    },
    {
      "name": "phrase_千方百计",
      "label": "Phrase 千方百计",
      "file": "output/intro.fr/default/html/concept_phrase_千方百计.html",
      "model": "default",
      "pinyin": "qianfangbaiji",
      "pinyin_initials": "qfbj"
    },
    {
      "name": "一",
      "label": "一",
      "file": "output/intro.fr/default/html/concept_一.html",
      "model": "default",
      "pinyin": "yi"
    },
    {
      "name": "万",
      "label": "万",
      "file": "output/intro.fr/default/html/concept_万.html",
      "model": "default",
      "pinyin": "wan"
    },
    {
      "name": "丨",
      "label": "丨",
      "file": "output/intro.fr/default/html/concept_丨.html",
      "model": "default",
      "pinyin": "shu"
    },
    {
      "name": "丶",
      "label": "丶",
      "file": "output/intro.fr/default/html/concept_丶.html",
      "model": "default",
      "pinyin": "zhu"
    },
    {
      "name": "丿",
      "label": "丿",
      "file": "output/intro.fr/default/html/concept_丿.html",
      "model": "default",
      "pinyin": "pie"
    },
    {
      "name": "十",
      "label": "十",
      "file": "output/intro.fr/default/html/concept_十.html",
      "model": "default",
      "pinyin": "shi"
    },
    {
      "name": "千",
      "label": "千",
      "file": "output/intro.fr/default/html/concept_千.html",
      "model": "default",
      "pinyin": "qian"
    },
    {
      "name": "方",
      "label": "方",
      "file": "output/intro.fr/default/html/concept_方.html",
      "model": "default",
      "pinyin": "fang"
    },
    {
      "name": "日",
      "label": "日",
      "file": "output/intro.fr/default/html/concept_日.html",
      "model": "default",
      "pinyin": "ri"
    },
    {
      "name": "白",
      "label": "白",
      "file": "output/intro.fr/default/html/concept_白.html",
      "model": "default",
      "pinyin": "bai"
    },
    {
      "name": "百",
      "label": "百",
      "file": "output/intro.fr/default/html/concept_百.html",
      "model": "default",
      "pinyin": "bai"
    },
    {
      "name": "讠",
      "label": "讠",
      "file": "output/intro.fr/default/html/concept_讠.html",
      "model": "default",
      "pinyin": "yan"
    },
    {
      "name": "计",
      "label": "计",
      "file": "output/intro.fr/default/html/concept_计.html",
      "model": "default",
      "pinyin": "ji"
    },
    {
      "name": "phrase_千方百计",
      "label": "Phrase 千方百计",
      "file": "output/intro.fr/gemma4/html/concept_phrase_千方百计.html",
      "model": "gemma4",
      "pinyin": "qianfangbaiji",
      "pinyin_initials": "qfbj"
    },
    {
      "name": "一",
      "label": "一",
      "file": "output/intro.fr/gemma4/html/concept_一.html",
      "model": "gemma4",
      "pinyin": "yi"
    },
    {
      "name": "万",
      "label": "万",
      "file": "output/intro.fr/gemma4/html/concept_万.html",
      "model": "gemma4",
      "pinyin": "wan"
    },
    {
      "name": "丨",
      "label": "丨",
      "file": "output/intro.fr/gemma4/html/concept_丨.html",
      "model": "gemma4",
      "pinyin": "shu"
    },
    {
      "name": "丶",
      "label": "丶",
      "file": "output/intro.fr/gemma4/html/concept_丶.html",
      "model": "gemma4",
      "pinyin": "zhu"
    },
    {
      "name": "丿",
      "label": "丿",
      "file": "output/intro.fr/gemma4/html/concept_丿.html",
      "model": "gemma4",
      "pinyin": "pie"
    },
    {
      "name": "十",
      "label": "十",
      "file": "output/intro.fr/gemma4/html/concept_十.html",
      "model": "gemma4",
      "pinyin": "shi"
    },
    {
      "name": "千",
      "label": "千",
      "file": "output/intro.fr/gemma4/html/concept_千.html",
      "model": "gemma4",
      "pinyin": "qian"
    },
    {
      "name": "方",
      "label": "方",
      "file": "output/intro.fr/gemma4/html/concept_方.html",
      "model": "gemma4",
      "pinyin": "fang"
    },
    {
      "name": "日",
      "label": "日",
      "file": "output/intro.fr/gemma4/html/concept_日.html",
      "model": "gemma4",
      "pinyin": "ri"
    },
    {
      "name": "白",
      "label": "白",
      "file": "output/intro.fr/gemma4/html/concept_白.html",
      "model": "gemma4",
      "pinyin": "bai"
    },
    {
      "name": "百",
      "label": "百",
      "file": "output/intro.fr/gemma4/html/concept_百.html",
      "model": "gemma4",
      "pinyin": "bai"
    },
    {
      "name": "讠",
      "label": "讠",
      "file": "output/intro.fr/gemma4/html/concept_讠.html",
      "model": "gemma4",
      "pinyin": "yan"
    },
    {
      "name": "计",
      "label": "计",
      "file": "output/intro.fr/gemma4/html/concept_计.html",
      "model": "gemma4",
      "pinyin": "ji"
    },
    {
      "name": "phrase_千方百计",
      "label": "Phrase 千方百计",
      "file": "output/intro.fr/sonnet/html/concept_phrase_千方百计.html",
      "model": "sonnet",
      "pinyin": "qianfangbaiji",
      "pinyin_initials": "qfbj"
    },
    {
      "name": "一",
      "label": "一",
      "file": "output/intro.fr/sonnet/html/concept_一.html",
      "model": "sonnet",
      "pinyin": "yi"
    },
    {
      "name": "万",
      "label": "万",
      "file": "output/intro.fr/sonnet/html/concept_万.html",
      "model": "sonnet",
      "pinyin": "wan"
    },
    {
      "name": "丨",
      "label": "丨",
      "file": "output/intro.fr/sonnet/html/concept_丨.html",
      "model": "sonnet",
      "pinyin": "shu"
    },
    {
      "name": "丶",
      "label": "丶",
      "file": "output/intro.fr/sonnet/html/concept_丶.html",
      "model": "sonnet",
      "pinyin": "zhu"
    },
    {
      "name": "丿",
      "label": "丿",
      "file": "output/intro.fr/sonnet/html/concept_丿.html",
      "model": "sonnet",
      "pinyin": "pie"
    },
    {
      "name": "十",
      "label": "十",
      "file": "output/intro.fr/sonnet/html/concept_十.html",
      "model": "sonnet",
      "pinyin": "shi"
    },
    {
      "name": "千",
      "label": "千",
      "file": "output/intro.fr/sonnet/html/concept_千.html",
      "model": "sonnet",
      "pinyin": "qian"
    },
    {
      "name": "方",
      "label": "方",
      "file": "output/intro.fr/sonnet/html/concept_方.html",
      "model": "sonnet",
      "pinyin": "fang"
    },
    {
      "name": "日",
      "label": "日",
      "file": "output/intro.fr/sonnet/html/concept_日.html",
      "model": "sonnet",
      "pinyin": "ri"
    },
    {
      "name": "白",
      "label": "白",
      "file": "output/intro.fr/sonnet/html/concept_白.html",
      "model": "sonnet",
      "pinyin": "bai"
    },
    {
      "name": "百",
      "label": "百",
      "file": "output/intro.fr/sonnet/html/concept_百.html",
      "model": "sonnet",
      "pinyin": "bai"
    },
    {
      "name": "讠",
      "label": "讠",
      "file": "output/intro.fr/sonnet/html/concept_讠.html",
      "model": "sonnet",
      "pinyin": "yan"
    },
    {
      "name": "计",
      "label": "计",
      "file": "output/intro.fr/sonnet/html/concept_计.html",
      "model": "sonnet",
      "pinyin": "ji"
    },
    {
      "name": "一",
      "label": "一",
      "file": "output/intro.ko/sonnet/html/concept_一.html",
      "model": "sonnet",
      "pinyin": "yi"
    },
    {
      "name": "万",
      "label": "万",
      "file": "output/intro.ko/sonnet/html/concept_万.html",
      "model": "sonnet",
      "pinyin": "wan"
    },
    {
      "name": "丨",
      "label": "丨",
      "file": "output/intro.ko/sonnet/html/concept_丨.html",
      "model": "sonnet",
      "pinyin": "shu"
    },
    {
      "name": "丶",
      "label": "丶",
      "file": "output/intro.ko/sonnet/html/concept_丶.html",
      "model": "sonnet",
      "pinyin": "zhu"
    },
    {
      "name": "丿",
      "label": "丿",
      "file": "output/intro.ko/sonnet/html/concept_丿.html",
      "model": "sonnet",
      "pinyin": "pie"
    },
    {
      "name": "十",
      "label": "十",
      "file": "output/intro.ko/sonnet/html/concept_十.html",
      "model": "sonnet",
      "pinyin": "shi"
    },
    {
      "name": "千",
      "label": "千",
      "file": "output/intro.ko/sonnet/html/concept_千.html",
      "model": "sonnet",
      "pinyin": "qian"
    },
    {
      "name": "方",
      "label": "方",
      "file": "output/intro.ko/sonnet/html/concept_方.html",
      "model": "sonnet",
      "pinyin": "fang"
    },
    {
      "name": "日",
      "label": "日",
      "file": "output/intro.ko/sonnet/html/concept_日.html",
      "model": "sonnet",
      "pinyin": "ri"
    },
    {
      "name": "白",
      "label": "白",
      "file": "output/intro.ko/sonnet/html/concept_白.html",
      "model": "sonnet",
      "pinyin": "bai"
    },
    {
      "name": "百",
      "label": "百",
      "file": "output/intro.ko/sonnet/html/concept_百.html",
      "model": "sonnet",
      "pinyin": "bai"
    },
    {
      "name": "讠",
      "label": "讠",
      "file": "output/intro.ko/sonnet/html/concept_讠.html",
      "model": "sonnet",
      "pinyin": "yan"
    },
    {
      "name": "计",
      "label": "计",
      "file": "output/intro.ko/sonnet/html/concept_计.html",
      "model": "sonnet",
      "pinyin": "ji"
    },
    {
      "name": "phrase_千方百计",
      "label": "Phrase 千方百计",
      "file": "output/intro.zh/default/html/concept_phrase_千方百计.html",
      "model": "default",
      "pinyin": "qianfangbaiji",
      "pinyin_initials": "qfbj"
    },
    {
      "name": "一",
      "label": "一",
      "file": "output/intro.zh/default/html/concept_一.html",
      "model": "default",
      "pinyin": "yi"
    },
    {
      "name": "万",
      "label": "万",
      "file": "output/intro.zh/default/html/concept_万.html",
      "model": "default",
      "pinyin": "wan"
    },
    {
      "name": "丨",
      "label": "丨",
      "file": "output/intro.zh/default/html/concept_丨.html",
      "model": "default",
      "pinyin": "shu"
    },
    {
      "name": "丶",
      "label": "丶",
      "file": "output/intro.zh/default/html/concept_丶.html",
      "model": "default",
      "pinyin": "zhu"
    },
    {
      "name": "丿",
      "label": "丿",
      "file": "output/intro.zh/default/html/concept_丿.html",
      "model": "default",
      "pinyin": "pie"
    },
    {
      "name": "十",
      "label": "十",
      "file": "output/intro.zh/default/html/concept_十.html",
      "model": "default",
      "pinyin": "shi"
    },
    {
      "name": "千",
      "label": "千",
      "file": "output/intro.zh/default/html/concept_千.html",
      "model": "default",
      "pinyin": "qian"
    },
    {
      "name": "方",
      "label": "方",
      "file": "output/intro.zh/default/html/concept_方.html",
      "model": "default",
      "pinyin": "fang"
    },
    {
      "name": "日",
      "label": "日",
      "file": "output/intro.zh/default/html/concept_日.html",
      "model": "default",
      "pinyin": "ri"
    },
    {
      "name": "白",
      "label": "白",
      "file": "output/intro.zh/default/html/concept_白.html",
      "model": "default",
      "pinyin": "bai"
    },
    {
      "name": "百",
      "label": "百",
      "file": "output/intro.zh/default/html/concept_百.html",
      "model": "default",
      "pinyin": "bai"
    },
    {
      "name": "讠",
      "label": "讠",
      "file": "output/intro.zh/default/html/concept_讠.html",
      "model": "default",
      "pinyin": "yan"
    },
    {
      "name": "计",
      "label": "计",
      "file": "output/intro.zh/default/html/concept_计.html",
      "model": "default",
      "pinyin": "ji"
    },
    {
      "name": "phrase_千方百计",
      "label": "Phrase 千方百计",
      "file": "output/intro.zh/gemma3/html/concept_phrase_千方百计.html",
      "model": "gemma3",
      "pinyin": "qianfangbaiji",
      "pinyin_initials": "qfbj"
    },
    {
      "name": "一",
      "label": "一",
      "file": "output/intro.zh/gemma3/html/concept_一.html",
      "model": "gemma3",
      "pinyin": "yi"
    },
    {
      "name": "万",
      "label": "万",
      "file": "output/intro.zh/gemma3/html/concept_万.html",
      "model": "gemma3",
      "pinyin": "wan"
    },
    {
      "name": "丨",
      "label": "丨",
      "file": "output/intro.zh/gemma3/html/concept_丨.html",
      "model": "gemma3",
      "pinyin": "shu"
    },
    {
      "name": "丶",
      "label": "丶",
      "file": "output/intro.zh/gemma3/html/concept_丶.html",
      "model": "gemma3",
      "pinyin": "zhu"
    },
    {
      "name": "丿",
      "label": "丿",
      "file": "output/intro.zh/gemma3/html/concept_丿.html",
      "model": "gemma3",
      "pinyin": "pie"
    },
    {
      "name": "十",
      "label": "十",
      "file": "output/intro.zh/gemma3/html/concept_十.html",
      "model": "gemma3",
      "pinyin": "shi"
    },
    {
      "name": "千",
      "label": "千",
      "file": "output/intro.zh/gemma3/html/concept_千.html",
      "model": "gemma3",
      "pinyin": "qian"
    },
    {
      "name": "方",
      "label": "方",
      "file": "output/intro.zh/gemma3/html/concept_方.html",
      "model": "gemma3",
      "pinyin": "fang"
    },
    {
      "name": "日",
      "label": "日",
      "file": "output/intro.zh/gemma3/html/concept_日.html",
      "model": "gemma3",
      "pinyin": "ri"
    },
    {
      "name": "白",
      "label": "白",
      "file": "output/intro.zh/gemma3/html/concept_白.html",
      "model": "gemma3",
      "pinyin": "bai"
    },
    {
      "name": "百",
      "label": "百",
      "file": "output/intro.zh/gemma3/html/concept_百.html",
      "model": "gemma3",
      "pinyin": "bai"
    },
    {
      "name": "讠",
      "label": "讠",
      "file": "output/intro.zh/gemma3/html/concept_讠.html",
      "model": "gemma3",
      "pinyin": "yan"
    },
    {
      "name": "计",
      "label": "计",
      "file": "output/intro.zh/gemma3/html/concept_计.html",
      "model": "gemma3",
      "pinyin": "ji"
    },
    {
      "name": "phrase_千方百计",
      "label": "Phrase 千方百计",
      "file": "output/intro.zh/gemma4/html/concept_phrase_千方百计.html",
      "model": "gemma4",
      "pinyin": "qianfangbaiji",
      "pinyin_initials": "qfbj"
    },
    {
      "name": "一",
      "label": "一",
      "file": "output/intro.zh/gemma4/html/concept_一.html",
      "model": "gemma4",
      "pinyin": "yi"
    },
    {
      "name": "万",
      "label": "万",
      "file": "output/intro.zh/gemma4/html/concept_万.html",
      "model": "gemma4",
      "pinyin": "wan"
    },
    {
      "name": "丨",
      "label": "丨",
      "file": "output/intro.zh/gemma4/html/concept_丨.html",
      "model": "gemma4",
      "pinyin": "shu"
    },
    {
      "name": "丶",
      "label": "丶",
      "file": "output/intro.zh/gemma4/html/concept_丶.html",
      "model": "gemma4",
      "pinyin": "zhu"
    },
    {
      "name": "丿",
      "label": "丿",
      "file": "output/intro.zh/gemma4/html/concept_丿.html",
      "model": "gemma4",
      "pinyin": "pie"
    },
    {
      "name": "十",
      "label": "十",
      "file": "output/intro.zh/gemma4/html/concept_十.html",
      "model": "gemma4",
      "pinyin": "shi"
    },
    {
      "name": "千",
      "label": "千",
      "file": "output/intro.zh/gemma4/html/concept_千.html",
      "model": "gemma4",
      "pinyin": "qian"
    },
    {
      "name": "方",
      "label": "方",
      "file": "output/intro.zh/gemma4/html/concept_方.html",
      "model": "gemma4",
      "pinyin": "fang"
    },
    {
      "name": "日",
      "label": "日",
      "file": "output/intro.zh/gemma4/html/concept_日.html",
      "model": "gemma4",
      "pinyin": "ri"
    },
    {
      "name": "白",
      "label": "白",
      "file": "output/intro.zh/gemma4/html/concept_白.html",
      "model": "gemma4",
      "pinyin": "bai"
    },
    {
      "name": "百",
      "label": "百",
      "file": "output/intro.zh/gemma4/html/concept_百.html",
      "model": "gemma4",
      "pinyin": "bai"
    },
    {
      "name": "讠",
      "label": "讠",
      "file": "output/intro.zh/gemma4/html/concept_讠.html",
      "model": "gemma4",
      "pinyin": "yan"
    },
    {
      "name": "计",
      "label": "计",
      "file": "output/intro.zh/gemma4/html/concept_计.html",
      "model": "gemma4",
      "pinyin": "ji"
    },
    {
      "name": "phrase_千方百计",
      "label": "Phrase 千方百计",
      "file": "output/intro.zh/sonnet/html/concept_phrase_千方百计.html",
      "model": "sonnet",
      "pinyin": "qianfangbaiji",
      "pinyin_initials": "qfbj"
    },
    {
      "name": "一",
      "label": "一",
      "file": "output/intro.zh/sonnet/html/concept_一.html",
      "model": "sonnet",
      "pinyin": "yi"
    },
    {
      "name": "万",
      "label": "万",
      "file": "output/intro.zh/sonnet/html/concept_万.html",
      "model": "sonnet",
      "pinyin": "wan"
    },
    {
      "name": "丨",
      "label": "丨",
      "file": "output/intro.zh/sonnet/html/concept_丨.html",
      "model": "sonnet",
      "pinyin": "shu"
    },
    {
      "name": "丶",
      "label": "丶",
      "file": "output/intro.zh/sonnet/html/concept_丶.html",
      "model": "sonnet",
      "pinyin": "zhu"
    },
    {
      "name": "丿",
      "label": "丿",
      "file": "output/intro.zh/sonnet/html/concept_丿.html",
      "model": "sonnet",
      "pinyin": "pie"
    },
    {
      "name": "十",
      "label": "十",
      "file": "output/intro.zh/sonnet/html/concept_十.html",
      "model": "sonnet",
      "pinyin": "shi"
    },
    {
      "name": "千",
      "label": "千",
      "file": "output/intro.zh/sonnet/html/concept_千.html",
      "model": "sonnet",
      "pinyin": "qian"
    },
    {
      "name": "方",
      "label": "方",
      "file": "output/intro.zh/sonnet/html/concept_方.html",
      "model": "sonnet",
      "pinyin": "fang"
    },
    {
      "name": "日",
      "label": "日",
      "file": "output/intro.zh/sonnet/html/concept_日.html",
      "model": "sonnet",
      "pinyin": "ri"
    },
    {
      "name": "白",
      "label": "白",
      "file": "output/intro.zh/sonnet/html/concept_白.html",
      "model": "sonnet",
      "pinyin": "bai"
    },
    {
      "name": "百",
      "label": "百",
      "file": "output/intro.zh/sonnet/html/concept_百.html",
      "model": "sonnet",
      "pinyin": "bai"
    },
    {
      "name": "讠",
      "label": "讠",
      "file": "output/intro.zh/sonnet/html/concept_讠.html",
      "model": "sonnet",
      "pinyin": "yan"
    },
    {
      "name": "计",
      "label": "计",
      "file": "output/intro.zh/sonnet/html/concept_计.html",
      "model": "sonnet",
      "pinyin": "ji"
    }
  ]
}
